heybrochecklog/__init__.py
heybrochecklog/__main__.py
heybrochecklog/analyze.py
heybrochecklog/logfile.py
heybrochecklog/markup/__init__.py
heybrochecklog/markup/matches.py
heybrochecklog/resources/__init__.py
heybrochecklog/resources/drives.db
heybrochecklog/resources/eac/bulgarian.json
heybrochecklog/resources/eac/chinese (simplified).json
heybrochecklog/resources/eac/czech.json
heybrochecklog/resources/eac/dutch.json
heybrochecklog/resources/eac/english.json
heybrochecklog/resources/eac/french.json
heybrochecklog/resources/eac/german.json
heybrochecklog/resources/eac/italian.json
heybrochecklog/resources/eac/polish.json
heybrochecklog/resources/eac/russian.json
heybrochecklog/resources/eac/serbian.json
heybrochecklog/resources/eac/slovak.json
heybrochecklog/resources/eac/spanish.json
heybrochecklog/resources/eac/swedish.json
heybrochecklog/resources/eac/uzbek.json
heybrochecklog/resources/eac95/chinese (simplified).json
heybrochecklog/resources/eac95/chinese (traditional).json
heybrochecklog/resources/eac95/croatian.json
heybrochecklog/resources/eac95/czech.json
heybrochecklog/resources/eac95/danish.json
heybrochecklog/resources/eac95/dutch.json
heybrochecklog/resources/eac95/english.json
heybrochecklog/resources/eac95/french.json
heybrochecklog/resources/eac95/german.json
heybrochecklog/resources/eac95/hungarian.json
heybrochecklog/resources/eac95/italian.json
heybrochecklog/resources/eac95/japanese.json
heybrochecklog/resources/eac95/korean.json
heybrochecklog/resources/eac95/norwegian.json
heybrochecklog/resources/eac95/portuguese-br.json
heybrochecklog/resources/eac95/portuguese.json
heybrochecklog/resources/eac95/russian.json
heybrochecklog/resources/eac95/serbian.json
heybrochecklog/resources/eac95/slovak.json
heybrochecklog/resources/eac95/spanish.json
heybrochecklog/resources/eac95/swedish.json
heybrochecklog/resources/eac95/taiwan.json
heybrochecklog/resources/eac95/ukrainian.json
heybrochecklog/resources/eac95/uzbek.json
heybrochecklog-1.3.2.dist-info/entry_points.txt
heybrochecklog-1.3.2.dist-info/LICENSE
heybrochecklog-1.3.2.dist-info/WHEEL
heybrochecklog-1.3.2.dist-info/METADATA
heybrochecklog-1.3.2.dist-info/RECORD
