Metadata-Version: 2.1
Name: heybrochecklog
Version: 1.3.2
Summary: A python tool for evaluating and working with EAC/XLD rip logs.
Home-page: https://github.com/ligh7s/hey-bro-check-log
License: Apache-2.0
Keywords: logchecker,eac,xld
Author: lights
Author-email: lights@tutanota.de
Requires-Python: >=3.5,<4.0
Classifier: License :: OSI Approved :: Apache Software License
Classifier: Programming Language :: Python :: 3
Classifier: Programming Language :: Python :: 3.5
Classifier: Programming Language :: Python :: 3.6
Classifier: Programming Language :: Python :: 3.7
Classifier: Programming Language :: Python :: 3.8
Requires-Dist: chardet (>=3.0.4,<4.0.0)
Project-URL: Repository, https://github.com/ligh7s/hey-bro-check-log
